<meta:Type
  xmlns:meta="class:/spiralcraft/data/types/meta"
  xmlns:ui="class:/spiralcraft/ui"
  >
  <fields>
    <meta:Field>
      <name>fieldURI
      </name>
      
      <type><URI.type/>
      </type>
    </meta:Field>
    
    <meta:Field>
      <name>label
      </name>
      
      <type><String.type/>
      </type>
    </meta:Field>
    
    <meta:Field>
      <name>controlModel
      </name>
      
      <type><ui:ViewModel.type/>
      </type>
    </meta:Field>
  </fields>


</meta:Type>